cryptocode/__init__.py
cryptocode/myfunctions.py
cryptocode-0.1.dist-info/LICENSE.txt
cryptocode-0.1.dist-info/METADATA
cryptocode-0.1.dist-info/WHEEL
cryptocode-0.1.dist-info/top_level.txt
cryptocode-0.1.dist-info/RECORD
