Metadata-Version: 2.1
Name: cryptocode
Version: 0.1
Summary: Python library used to encrypt and decrypt strings in the simplest possible way.
Home-page: https://github.com/gdavid7/cryptocode
Author: gdavid7
License: MIT
Keywords: cryptocode,key,crypto,encodestring
Platform: UNKNOWN
Classifier: Programming Language :: Python :: 3
Classifier: License :: OSI Approved :: MIT License
Classifier: Operating System :: OS Independent
